setup.cfg
setup.py
fetchopenfmri/__init__.py
fetchopenfmri/fetch.py
fetchopenfmri.egg-info/PKG-INFO
fetchopenfmri.egg-info/SOURCES.txt
fetchopenfmri.egg-info/dependency_links.txt
fetchopenfmri.egg-info/entry_points.txt
fetchopenfmri.egg-info/top_level.txt