Metadata-Version: 1.1
Name: fetchopenfmri
Version: 1.0.3
Summary: Fetches files for the latest version of an openfMRI dataset
Home-page: https://www.github.com/wiheto/fetchopenfmri
Author: William Hedley Thompson
Author-email: hedley@startmail.com
License: UNKNOWN
Download-URL: https://github.com/wiheto/fetchopenfmri/archive/v1.0.1.tar.gz
Keywords: openfmri,open data,fmri
Platform: UNKNOWN
